{
  "minecraft:recipes/decorations/crafting_table": {
    "criteria": {
      "unlock_right_away": "2023-04-22 20:54:28 +0900"
    },
    "done": true
  },
  "minecraft:adventure/adventuring_time": {
    "criteria": {
      "minecraft:plains": "2023-04-22 20:54:29 +0900"
    },
    "done": false
  },
  "minecraft:adventure/root": {
    "criteria": {
      "killed_by_something": "2023-04-22 21:19:04 +0900"
    },
    "done": true
  },
  "minecraft:recipes/redstone/redstone_torch": {
    "criteria": {
      "has_redstone": "2023-04-22 21:24:50 +0900"
    },
    "done": true
  },
  "minecraft:recipes/tools/clock": {
    "criteria": {
      "has_redstone": "2023-04-22 21:24:50 +0900"
    },
    "done": true
  },
  "minecraft:recipes/redstone/dropper": {
    "criteria": {
      "has_redstone": "2023-04-22 21:24:50 +0900"
    },
    "done": true
  },
  "minecraft:recipes/redstone/redstone_block": {
    "criteria": {
      "has_redstone": "2023-04-22 21:24:50 +0900"
    },
    "done": true
  },
  "minecraft:recipes/redstone/note_block": {
    "criteria": {
      "has_redstone": "2023-04-22 21:24:50 +0900"
    },
    "done": true
  },
  "minecraft:recipes/redstone/target": {
    "criteria": {
      "has_redstone": "2023-04-22 21:24:50 +0900"
    },
    "done": true
  },
  "minecraft:recipes/tools/compass": {
    "criteria": {
      "has_redstone": "2023-04-22 21:24:50 +0900"
    },
    "done": true
  },
  "minecraft:recipes/redstone/piston": {
    "criteria": {
      "has_redstone": "2023-04-22 21:24:50 +0900"
    },
    "done": true
  },
  "DataVersion": 3337
}